README.rst
setup.py
census2dbf/__init__.py
census2dbf/censuscsv.py
census2dbf/cli.py
census2dbf/dbfwriter.py
census2dbf.egg-info/PKG-INFO
census2dbf.egg-info/SOURCES.txt
census2dbf.egg-info/dependency_links.txt
census2dbf.egg-info/entry_points.txt
census2dbf.egg-info/top_level.txt
census2dbf.egg-info/zip-safe