Metadata-Version: 1.1
Name: census2dbf
Version: 0.2.0
Summary: Convert US Census CSV files into DBFs
Home-page: https://github.com/fitnr/census2dbf
Author: Neil Freeman
Author-email: contact@fakeisthenewreal.org
License: GPLv3
Keywords: GIS DBF Census
Platform: UNKNOWN
Classifier: Intended Audience :: Developers
Classifier: License :: OSI Approved :: GNU General Public License v3 (GPLv3)
Classifier: Natural Language :: English
Classifier: Topic :: Database
Classifier: Programming Language :: Python :: 2.7
Classifier: Programming Language :: Python :: 3.4
Classifier: Programming Language :: Python :: Implementation :: PyPy
Classifier: Operating System :: OS Independent
